LICENSE
MANIFEST.in
README.md
pyproject.toml
setup.cfg
setup.py
django_payment_gateways/__init__.py
django_payment_gateways/apps.py
django_payment_gateways/exceptions.py
django_payment_gateways/tests.py
django_payment_gateways.egg-info/PKG-INFO
django_payment_gateways.egg-info/SOURCES.txt
django_payment_gateways.egg-info/dependency_links.txt
django_payment_gateways.egg-info/requires.txt
django_payment_gateways.egg-info/top_level.txt
django_payment_gateways/modules/PaymentWorker.py
django_payment_gateways/modules/__init__.py
django_payment_gateways/modules/invoice.py
django_payment_gateways/modules/abstracts/__init__.py
django_payment_gateways/modules/abstracts/driver.py
django_payment_gateways/modules/abstracts/receipt.py
django_payment_gateways/modules/drivers/__init__.py
django_payment_gateways/modules/drivers/parsian/__init__.py
django_payment_gateways/modules/drivers/parsian/parsian.py
django_payment_gateways/modules/drivers/parsian/strategies/__init__.py
django_payment_gateways/modules/drivers/parsian/strategies/normal.py
django_payment_gateways/modules/drivers/parsian/strategies/sandbox.py
django_payment_gateways/modules/drivers/zarinpal/__init__.py
django_payment_gateways/modules/drivers/zarinpal/zarinpal.py
django_payment_gateways/modules/drivers/zarinpal/strategies/__init__.py
django_payment_gateways/modules/drivers/zarinpal/strategies/sandbox.py